{
  "error": 0,
  "message": "success",
  "data": {
    "page": 1,
    "pageSize": 20,
    "nextPage": 1,
    "prevPage": 1,
    "totalPages": 1,
    "totalRecords": 19,
    "records": [
      {
        "id": 5646529,
        "tid": "FT24033409994719\\BNK",
        "description": "CUSTOMER abc-123456 - HUYNH TAN LOC - SearchCV  Ma giao dich  Trace939636 Trace 93 9636",
        "amount": 20000,
        "cusumBalance": 20000,
        "when": "2024-02-02T16:42:00",
        "bookingDate": null,
        "bankSubAccId": "0377081411",
        "paymentChannel": "",
        "virtualAccount": "",
        "virtualAccountName": "",
        "corresponsiveName": "",
        "corresponsiveAccount": "",
        "corresponsiveBankId": "",
        "corresponsiveBankName": "",
        "accountId": 7050,
        "bankCodeName": "mbbank"
      },
      {
        "id": 5646385,
        "tid": "FT24033240162500",
        "description": "CUSTOMER 576ty4836 HUYNH TAN LOC chuyen khoan - Ma gia o dich/ Trace 795855",
        "amount": -20000,
        "cusumBalance": 0,
        "when": "2024-02-02T16:28:00",
        "bookingDate": null,
        "bankSubAccId": "0377081411",
        "paymentChannel": "",
        "virtualAccount": "",
        "virtualAccountName": "",
        "corresponsiveName": "HUYNH TAN LOC",
        "corresponsiveAccount": "0004100029624002",
        "corresponsiveBankId": "",
        "corresponsiveBankName": "OCB-Ngân hàng TMCP Phương Đông",
        "accountId": 7050,
        "bankCodeName": "mbbank"
      },
      {
        "id": 5646321,
        "tid": "FT24033068426604\\BNK",
        "description": "CUSTOMER 129698 Huynh Tan Loc SearchCV   Ma  giao dich  Trace924284 Trace 924284",
        "amount": 20000,
        "cusumBalance": 20000,
        "when": "2024-02-02T16:13:00",
        "bookingDate": null,
        "bankSubAccId": "0377081411",
        "paymentChannel": "",
        "virtualAccount": "",
        "virtualAccountName": "",
        "corresponsiveName": "",
        "corresponsiveAccount": "",
        "corresponsiveBankId": "",
        "corresponsiveBankName": "",
        "accountId": 7050,
        "bankCodeName": "mbbank"
      },
      {
        "id": 5646325,
        "tid": "FT24033834095869",
        "description": "CUSTOMER HUYNH TAN LOC chuyen khoan - Ma gia o dich/ Trace 619921",
        "amount": -20000,
        "cusumBalance": 0,
        "when": "2024-02-02T16:05:00",
        "bookingDate": null,
        "bankSubAccId": "0377081411",
        "paymentChannel": "",
        "virtualAccount": "",
        "virtualAccountName": "",
        "corresponsiveName": "HUYNH TAN LOC",
        "corresponsiveAccount": "0004100029624002",
        "corresponsiveBankId": "",
        "corresponsiveBankName": "OCB-Ngân hàng TMCP Phương Đông",
        "accountId": 7050,
        "bankCodeName": "mbbank"
      },
      {
        "id": 5646324,
        "tid": "FT24033214069040\\BNK",
        "description": "CUSTOMER 028710   Huynh Tan Loc   PostJob    Ma giao dich  Trace904303 Trace 904 303",
        "amount": 20000,
        "cusumBalance": 20000,
        "when": "2024-02-02T15:35:00",
        "bookingDate": null,
        "bankSubAccId": "0377081411",
        "paymentChannel": "",
        "virtualAccount": "",
        "virtualAccountName": "",
        "corresponsiveName": "",
        "corresponsiveAccount": "",
        "corresponsiveBankId": "",
        "corresponsiveBankName": "",
        "accountId": 7050,
        "bankCodeName": "mbbank"
      },
      {
        "id": 5646322,
        "tid": "FT24026467827905",
        "description": "CUSTOMER                             - Ma gi ao dich/ Trace 316556",
        "amount": -30000,
        "cusumBalance": 0,
        "when": "2024-01-26T15:45:00",
        "bookingDate": null,
        "bankSubAccId": "0377081411",
        "paymentChannel": "",
        "virtualAccount": "",
        "virtualAccountName": "",
        "corresponsiveName": "",
        "corresponsiveAccount": "",
        "corresponsiveBankId": "",
        "corresponsiveBankName": "",
        "accountId": 7050,
        "bankCodeName": "mbbank"
      },
      {
        "id": 5646319,
        "tid": "FT24018270008078\\BNK",
        "description": "CUSTOMER IBFT Tru tien NGAY LAP TUC   Ma gia o dich  Trace724328 Trace 724328",
        "amount": 15000,
        "cusumBalance": 30000,
        "when": "2024-01-18T21:53:00",
        "bookingDate": null,
        "bankSubAccId": "0377081411",
        "paymentChannel": "",
        "virtualAccount": "",
        "virtualAccountName": "",
        "corresponsiveName": "",
        "corresponsiveAccount": "",
        "corresponsiveBankId": "",
        "corresponsiveBankName": "",
        "accountId": 7050,
        "bankCodeName": "mbbank"
      },
      {
        "id": 5646323,
        "tid": "FT24018548637960\\BNK",
        "description": "CUSTOMER IBFT ShareCV chuyen tien cho CTV       Ma giao dich  Trace714465 Trace  714465",
        "amount": 15000,
        "cusumBalance": 15000,
        "when": "2024-01-18T21:42:00",
        "bookingDate": null,
        "bankSubAccId": "0377081411",
        "paymentChannel": "",
        "virtualAccount": "",
        "virtualAccountName": "",
        "corresponsiveName": "",
        "corresponsiveAccount": "",
        "corresponsiveBankId": "",
        "corresponsiveBankName": "",
        "accountId": 7050,
        "bankCodeName": "mbbank"
      },
      {
        "id": 5646315,
        "tid": "FT24018603851107",
        "description": "CUSTOMER ShareCV thuc hien giao dich PostJob  - Ma giao dich/ Trace 265714",
        "amount": -5000,
        "cusumBalance": 0,
        "when": "2024-01-18T21:28:00",
        "bookingDate": null,
        "bankSubAccId": "0377081411",
        "paymentChannel": "",
        "virtualAccount": "",
        "virtualAccountName": "",
        "corresponsiveName": "HUYNH TAN LOC",
        "corresponsiveAccount": "040105912619",
        "corresponsiveBankId": "",
        "corresponsiveBankName": "STB Ngan hang TMCP Sai Gon Thuong Tin",
        "accountId": 7050,
        "bankCodeName": "mbbank"
      },
      {
        "id": 5646320,
        "tid": "FT24018531571190\\BNK",
        "description": "CUSTOMER IBFT HUYNH TAN LOC chuyen tien   Ma  giao dich  Trace697696 Trace 69769",
        "amount": 5000,
        "cusumBalance": 5000,
        "when": "2024-01-18T21:24:00",
        "bookingDate": null,
        "bankSubAccId": "0377081411",
        "paymentChannel": "",
        "virtualAccount": "",
        "virtualAccountName": "",
        "corresponsiveName": "",
        "corresponsiveAccount": "",
        "corresponsiveBankId": "",
        "corresponsiveBankName": "",
        "accountId": 7050,
        "bankCodeName": "mbbank"
      },
      {
        "id": 5646316,
        "tid": "FT24018826504984",
        "description": "CUSTOMER HUYNH TAN LOC chuyen khoan - Ma gia o dich/ Trace 228431",
        "amount": -30000,
        "cusumBalance": 0,
        "when": "2024-01-18T21:20:00",
        "bookingDate": null,
        "bankSubAccId": "0377081411",
        "paymentChannel": "",
        "virtualAccount": "",
        "virtualAccountName": "",
        "corresponsiveName": "HUYNH TAN LOC",
        "corresponsiveAccount": "040105912619",
        "corresponsiveBankId": "",
        "corresponsiveBankName": "STB Ngan hang TMCP Sai Gon Thuong Tin",
        "accountId": 7050,
        "bankCodeName": "mbbank"
      },
      {
        "id": 5646317,
        "tid": "FT24018057195760\\BNK",
        "description": "CUSTOMER IBFT HUYNH TAN LOC chuyen tien   Ma  giao dich  Trace686268 Trace 68626",
        "amount": 10000,
        "cusumBalance": 30000,
        "when": "2024-01-18T21:13:00",
        "bookingDate": null,
        "bankSubAccId": "0377081411",
        "paymentChannel": "",
        "virtualAccount": "",
        "virtualAccountName": "",
        "corresponsiveName": "",
        "corresponsiveAccount": "",
        "corresponsiveBankId": "",
        "corresponsiveBankName": "",
        "accountId": 7050,
        "bankCodeName": "mbbank"
      },
      {
        "id": 5646318,
        "tid": "FT24018333201077\\BNK",
        "description": "CUSTOMER IBFT HUYNH TAN LOC chuyen tien   Ma  giao dich  Trace545068 Trace 54506",
        "amount": 20000,
        "cusumBalance": 20000,
        "when": "2024-01-18T19:23:00",
        "bookingDate": null,
        "bankSubAccId": "0377081411",
        "paymentChannel": "",
        "virtualAccount": "",
        "virtualAccountName": "",
        "corresponsiveName": "",
        "corresponsiveAccount": "",
        "corresponsiveBankId": "",
        "corresponsiveBankName": "",
        "accountId": 7050,
        "bankCodeName": "mbbank"
      },
      {
        "id": 5646313,
        "tid": "FT24018741133055",
        "description": "CUSTOMER HUYNH TAN LOC chuyen khoan - Ma gia o dich/ Trace 191596",
        "amount": -60000,
        "cusumBalance": 0,
        "when": "2024-01-18T17:42:00",
        "bookingDate": null,
        "bankSubAccId": "0377081411",
        "paymentChannel": "",
        "virtualAccount": "",
        "virtualAccountName": "",
        "corresponsiveName": "HUYNH TAN LOC",
        "corresponsiveAccount": "040105912619",
        "corresponsiveBankId": "",
        "corresponsiveBankName": "STB Ngan hang TMCP Sai Gon Thuong Tin",
        "accountId": 7050,
        "bankCodeName": "mbbank"
      },
      {
        "id": 5646310,
        "tid": "FT24018078990036\\BNK",
        "description": "CUSTOMER IBFT HUYNH TAN LOC chuyen tien   Ma  giao dich  Trace390108 Trace 39010",
        "amount": 20000,
        "cusumBalance": 60000,
        "when": "2024-01-18T17:38:00",
        "bookingDate": null,
        "bankSubAccId": "0377081411",
        "paymentChannel": "",
        "virtualAccount": "",
        "virtualAccountName": "",
        "corresponsiveName": "",
        "corresponsiveAccount": "",
        "corresponsiveBankId": "",
        "corresponsiveBankName": "",
        "accountId": 7050,
        "bankCodeName": "mbbank"
      },
      {
        "id": 5646314,
        "tid": "FT24018075722209\\BNK",
        "description": "CUSTOMER IBFT HUYNH TAN LOC chuyen tien   Ma  giao dich  Trace387072 Trace 38707",
        "amount": 20000,
        "cusumBalance": 40000,
        "when": "2024-01-18T17:32:00",
        "bookingDate": null,
        "bankSubAccId": "0377081411",
        "paymentChannel": "",
        "virtualAccount": "",
        "virtualAccountName": "",
        "corresponsiveName": "",
        "corresponsiveAccount": "",
        "corresponsiveBankId": "",
        "corresponsiveBankName": "",
        "accountId": 7050,
        "bankCodeName": "mbbank"
      },
      {
        "id": 5646326,
        "tid": "FT24018691214478\\BNK",
        "description": "CUSTOMER IBFT HUYNH TAN LOC chuyen tien   Ma  giao dich  Trace375222 Trace 37522",
        "amount": 20000,
        "cusumBalance": 20000,
        "when": "2024-01-18T17:24:00",
        "bookingDate": null,
        "bankSubAccId": "0377081411",
        "paymentChannel": "",
        "virtualAccount": "",
        "virtualAccountName": "",
        "corresponsiveName": "",
        "corresponsiveAccount": "",
        "corresponsiveBankId": "",
        "corresponsiveBankName": "",
        "accountId": 7050,
        "bankCodeName": "mbbank"
      },
      {
        "id": 5646312,
        "tid": "FT24018994673004",
        "description": "CUSTOMER HUYNH TAN LOC chuyen khoan - Ma gia o dich/ Trace 079933",
        "amount": -20000,
        "cusumBalance": 0,
        "when": "2024-01-18T15:15:00",
        "bookingDate": null,
        "bankSubAccId": "0377081411",
        "paymentChannel": "",
        "virtualAccount": "",
        "virtualAccountName": "",
        "corresponsiveName": "HUYNH TAN LOC",
        "corresponsiveAccount": "040105912619",
        "corresponsiveBankId": "",
        "corresponsiveBankName": "STB Ngan hang TMCP Sai Gon Thuong Tin",
        "accountId": 7050,
        "bankCodeName": "mbbank"
      },
      {
        "id": 5646311,
        "tid": "FT24018051147037\\BNK",
        "description": "CUSTOMER IBFT HUYNH TAN LOC chuyen tien   Ma  giao dich  Trace178863 Trace 17886",
        "amount": 20000,
        "cusumBalance": 20000,
        "when": "2024-01-18T15:02:00",
        "bookingDate": null,
        "bankSubAccId": "0377081411",
        "paymentChannel": "",
        "virtualAccount": "",
        "virtualAccountName": "",
        "corresponsiveName": "",
        "corresponsiveAccount": "",
        "corresponsiveBankId": "",
        "corresponsiveBankName": "",
        "accountId": 7050,
        "bankCodeName": "mbbank"
      }
    ]
  }
}